tatoo-0.7.0.dist-info/zip-safe
tatoo-0.7.0.dist-info/RECORD
tatoo-0.7.0.dist-info/DESCRIPTION.rst
tatoo-0.7.0.dist-info/METADATA
tatoo-0.7.0.dist-info/top_level.txt
tatoo-0.7.0.dist-info/metadata.json
tatoo-0.7.0.dist-info/WHEEL
tatoo/einfo.py
tatoo/_version.py
tatoo/log.py
tatoo/settings.py
tatoo/exceptions.py
tatoo/signals.py
tatoo/interfaces.py
tatoo/__init__.py
tatoo/extension.py
tatoo/environment.py
tatoo/utils/lazy.py
tatoo/utils/manager.py
tatoo/utils/text.py
tatoo/utils/encoding.py
tatoo/utils/imports.py
tatoo/utils/serialization.py
tatoo/utils/times.py
tatoo/utils/__init__.py
tatoo/utils/datastructures.py
tatoo/utils/bugreport.py
tatoo/utils/dispatch/weakref_backports.py
tatoo/utils/dispatch/dispatch.py
tatoo/utils/dispatch/__init__.py
tatoo/task/handler.py
tatoo/task/base.py
tatoo/task/result.py
tatoo/task/trace.py
tatoo/task/types.py
tatoo/task/parameter.py
tatoo/task/__init__.py
