Metadata-Version: 2.0
Name: tatoo
Version: 0.7.0
Summary: Task execution framework
Home-page: https://github.com/malinoff/tatoo
Author: Dmitry Malinovsky
Author-email: damalinov@gmail.com
License: BSD-3
Keywords: task execution framework
Platform: linux
Platform: osx
Platform: windows
Classifier: Development Status :: 4 - Beta
Classifier: Intended Audience :: Developers
Classifier: Natural Language :: English
Classifier: Programming Language :: Python :: 2
Classifier: Programming Language :: Python :: 2.6
Classifier: Programming Language :: Python :: 2.7
Classifier: Programming Language :: Python :: 3
Classifier: Programming Language :: Python :: 3.3
Classifier: Programming Language :: Python :: 3.4
Classifier: Programming Language :: Python :: Implementation :: CPython
Classifier: Programming Language :: Python :: Implementation :: PyPy
Requires-Dist: wheel (>=0.24.0)
Requires-Dist: six (>=1.9.0)
Requires-Dist: logutils (>=0.3.3)
Requires-Dist: zope.interface (>=4.1.2)
Requires-Dist: importlib (>=1.0); python_version=='2.6'
Requires-Dist: funcsigs (>=0.4); python_version=='2.6' or python_version=='2.7'
